{"Sleep": ["is", "occurs", "deprivation"], "is": ["a", "associated", "native", "often", "explained", "generated", "blue", "then", "also", "a"], "a": ["fundamental", "consistent", "divine", "form", "series", "boosted", "renewable", "crucial", "highly", "remarkably", "vital", "form", "central", "blockchain,", "decentralized", "droplet,", "visible"], "fundamental": ["biological", "forces:"], "biological": ["process"], "process": ["that", "results"], "that": ["affects", "promote", "governs", "relies", "appears"], "affects": ["every"], "every": ["aspect"], "aspect": ["of"], "of": ["human", "sleep", "non-REM", "maintaining", "currency.", "steps,", "planes", "four", "the", "Bernoulli's", "motion", "copper-based", "their", "endorphins,", "happiness.", "the", "Defense", "devices,", "digital", "a", "light", "colors"], "human": ["health.", "brain"], "health.": ["The"], "The": ["average", "ability", "principles", "human", "internet"], "average": ["adult"], "adult": ["requires"], "requires": ["seven"], "seven": ["to"], "to": ["nine", "Central", "be", "fly", "gravity.", "the", "escape", "fit", "different", "incorporate", "generate", "heat", "the", "enable", "share", "the", "transform", "form"], "nine": ["hours"], "hours": ["of"], "sleep": ["per", "includes", "is", "schedule."], "per": ["night,"], "night,": ["though"], "though": ["individual"], "individual": ["needs"], "needs": ["vary."], "vary.": ["Sleep"], "occurs": ["in"], "in": ["cycles", "religious", "daily", "the", "solar", "reducing", "2009,", "the", "the"], "cycles": ["consisting"], "consisting": ["of"], "non-REM": ["and"], "and": ["REM", "immune", "South", "Aztecs", "even", "grinding", "weight.", "weight", "Newton's", "their", "each", "ability", "communication.", "a", "yoga", "maintain", "decreasing", "memories.", "cushioned", "made", "commerce.", "distributed", "the", "reflection", "separates", "exits"], "REM": ["stages.", "sleep"], "stages.": ["Non-REM"], "Non-REM": ["sleep"], "includes": ["deep"], "deep": ["restorative"], "restorative": ["phases,"], "phases,": ["while"], "while": ["REM"], "associated": ["with"], "with": ["vivid", "unique"], "vivid": ["dreaming."], "dreaming.": ["Sleep"], "deprivation": ["can"], "can": ["negatively", "regrow", "compress", "cater"], "negatively": ["impact"], "impact": ["memory,", "and"], "memory,": ["mood,"], "mood,": ["and", "and"], "immune": ["function,", "system."], "function,": ["emphasizing"], "emphasizing": ["the"], "the": ["importance", "cacao", "Mayans", "interplay", "aerodynamic", "wings,", "plane", "plane's", "wings", "lift", "presence", "release", "brain", "other", "brain", "body's", "skull", "1960s", "U.S.", "World", "internet", "public.", "internet", "first", "potential", "need", "refraction,", "droplet's", "iconic", "sky,", "sun."], "importance": ["of"], "maintaining": ["a"], "consistent": ["sleep"], "schedule.": ["Chocolate"], "Chocolate": ["originated"], "originated": ["from"], "from": ["the"], "cacao": ["tree,", "to", "beans."], "tree,": ["scientifically"], "scientifically": ["known"], "known": ["as", "for", "for"], "as": ["*Theobroma", "the", "a", "they", "small", "their", "walking,", "a"], "*Theobroma": ["cacao*,"], "cacao*,": ["which"], "which": ["is", "are", "is", "revolutionized"], "native": ["to"], "Central": ["and"], "South": ["America."], "America.": ["Ancient"], "Ancient": ["civilizations"], "civilizations": ["such"], "such": ["as", "as"], "Mayans": ["and"], "Aztecs": ["considered"], "considered": ["cacao", "healthier"], "be": ["a"], "divine": ["gift,"], "gift,": ["using"], "using": ["it"], "it": ["in", "downward", "easier", "bends"], "religious": ["ceremonies"], "ceremonies": ["and"], "even": ["as", "when"], "form": ["of", "of", "a"], "currency.": ["Modern"], "Modern": ["chocolate"], "chocolate": ["production"], "production": ["involves"], "involves": ["a"], "series": ["of"], "steps,": ["including"], "including": ["fermenting,", "improved"], "fermenting,": ["drying,"], "drying,": ["roasting,"], "roasting,": ["and"], "grinding": ["cacao"], "beans.": ["Dark"], "Dark": ["chocolate,"], "chocolate,": ["known"], "for": ["its", "flight.", "their", "camouflage", "individuals", "communication,", "security.", "regulatory"], "its": ["rich", "own", "power,", "origins", "component"], "rich": ["antioxidant"], "antioxidant": ["content,"], "content,": ["is"], "often": ["considered"], "healthier": ["than"], "than": ["milk"], "milk": ["or"], "or": ["white", "heat.", "air.", "virtual"], "white": ["chocolate."], "chocolate.": ["The"], "ability": ["of", "to"], "planes": ["to"], "fly": ["is"], "explained": ["by"], "by": ["the", "the", "an", "the", "cerebrospinal", "the"], "interplay": ["of"], "four": ["fundamental"], "forces:": ["lift,"], "lift,": ["thrust,"], "thrust,": ["drag,"], "drag,": ["and"], "weight.": ["Lift"], "Lift": ["is"], "generated": ["by"], "aerodynamic": ["shape"], "shape": ["of"], "wings,": ["thrust"], "thrust": ["propels"], "propels": ["the"], "plane": ["forward"], "forward": ["via"], "via": ["engines,"], "engines,": ["drag"], "drag": ["opposes"], "opposes": ["the"], "plane's": ["motion,"], "motion,": ["and"], "weight": ["pulls"], "pulls": ["it"], "downward": ["due"], "due": ["to", "to"], "gravity.": ["The"], "principles": ["of"], "Bernoulli's": ["theorem"], "theorem": ["and"], "Newton's": ["third"], "third": ["law"], "law": ["of"], "motion": ["explain"], "explain": ["how"], "how": ["pressure"], "pressure": ["differences"], "differences": ["over"], "over": ["the", "long"], "wings": ["create"], "create": ["the"], "lift": ["necessary"], "necessary": ["for"], "flight.": ["Octopuses"], "Octopuses": ["are", "are"], "are": ["fascinating", "known", "natural", "recorded", "optical"], "fascinating": ["marine"], "marine": ["animals"], "animals": ["with"], "unique": ["features."], "features.": ["They"], "They": ["have", "use"], "have": ["three", "the"], "three": ["hearts,", "pounds"], "hearts,": ["and"], "their": ["blood", "eight", "intelligence", "bodies", "beak.", "routines"], "blood": ["is"], "blue": ["due"], "presence": ["of"], "copper-based": ["hemocyanin."], "hemocyanin.": ["These"], "These": ["creatures", "neurons"], "creatures": ["can"], "regrow": ["lost"], "lost": ["arms,"], "arms,": ["and"], "each": ["of"], "eight": ["arms"], "arms": ["has"], "has": ["its"], "own": ["mini-brain,"], "mini-brain,": ["giving"], "giving": ["them"], "them": ["remarkable"], "remarkable": ["dexterity."], "dexterity.": ["Octopuses"], "intelligence": ["and"], "escape": ["through"], "through": ["tiny", "spaces", "synapses,"], "tiny": ["openings,"], "openings,": ["as"], "they": ["can", "also"], "compress": ["their"], "bodies": ["to"], "fit": ["through"], "spaces": ["as"], "small": ["as"], "beak.": ["They"], "use": ["specialized"], "specialized": ["color-changing"], "color-changing": ["cells,"], "cells,": ["called"], "called": ["chromatophores,"], "chromatophores,": ["for"], "camouflage": ["and"], "communication.": ["Engaging"], "Engaging": ["in"], "daily": ["physical"], "physical": ["activity"], "activity": ["provides"], "provides": ["numerous"], "numerous": ["health"], "health": ["benefits,"], "benefits,": ["including"], "improved": ["cardiovascular"], "cardiovascular": ["health,"], "health,": ["stronger"], "stronger": ["muscles,"], "muscles,": ["enhanced"], "enhanced": ["mood,"], "boosted": ["immune"], "system.": ["Exercise", "While"], "Exercise": ["stimulates"], "stimulates": ["the"], "release": ["of"], "endorphins,": ["which"], "natural": ["chemicals", "process"], "chemicals": ["in"], "brain": ["that", "weighs", "consumes"], "promote": ["feelings"], "feelings": ["of"], "happiness.": ["Activities"], "Activities": ["such"], "walking,": ["swimming,"], "swimming,": ["and"], "yoga": ["can"], "cater": ["to"], "different": ["fitness"], "fitness": ["levels,"], "levels,": ["making"], "making": ["it"], "easier": ["for"], "individuals": ["to"], "incorporate": ["exercise"], "exercise": ["into"], "into": ["their", "direct", "alternating", "its"], "routines": ["and"], "maintain": ["consistency."], "consistency.": ["Solar"], "Solar": ["energy", "thermal"], "energy": ["harnesses", "source,"], "harnesses": ["sunlight"], "sunlight": ["to", "to", "enters"], "generate": ["electricity"], "electricity": ["or"], "heat.": ["Photovoltaic"], "Photovoltaic": ["cells"], "cells": ["in"], "solar": ["panels", "power"], "panels": ["convert"], "convert": ["light"], "light": ["into", "within"], "direct": ["current"], "current": ["electricity,", "by"], "electricity,": ["which"], "then": ["transformed"], "transformed": ["into"], "alternating": ["current"], "an": ["inverter."], "inverter.": ["Solar"], "thermal": ["systems,"], "systems,": ["on", "they"], "on": ["the", "fossil", "cryptography", "a"], "other": ["hand,"], "hand,": ["directly"], "directly": ["capture"], "capture": ["sunlight"], "heat": ["water"], "water": ["or", "droplets."], "air.": ["As"], "As": ["a"], "renewable": ["energy"], "source,": ["solar"], "power": ["plays"], "plays": ["a"], "crucial": ["role"], "role": ["in"], "reducing": ["greenhouse"], "greenhouse": ["gas"], "gas": ["emissions"], "emissions": ["and"], "decreasing": ["reliance"], "reliance": ["on"], "fossil": ["fuels."], "fuels.": ["The"], "weighs": ["about"], "about": ["three"], "pounds": ["but"], "but": ["contains"], "contains": ["approximately"], "approximately": ["86"], "86": ["billion"], "billion": ["neurons."], "neurons.": ["These"], "neurons": ["communicate"], "communicate": ["through"], "synapses,": ["forming"], "forming": ["a"], "highly": ["complex"], "complex": ["network"], "network": ["that"], "governs": ["thoughts,"], "thoughts,": ["emotions,"], "emotions,": ["and"], "memories.": ["Despite"], "Despite": ["its"], "power,": ["the"], "consumes": ["roughly"], "roughly": ["20"], "20": ["percent"], "percent": ["of"], "body's": ["energy,"], "energy,": ["even"], "when": ["at", "the"], "at": ["rest."], "rest.": ["It"], "It": ["is"], "also": ["a", "raise"], "remarkably": ["fragile"], "fragile": ["organ,"], "organ,": ["protected"], "protected": ["by"], "skull": ["and"], "cushioned": ["by"], "cerebrospinal": ["fluid."], "fluid.": ["The"], "internet": ["traces", "accessible", "connects"], "traces": ["its"], "origins": ["to"], "1960s": ["when"], "U.S.": ["Department"], "Department": ["of"], "Defense": ["developed"], "developed": ["ARPANET"], "ARPANET": ["to"], "enable": ["computers"], "computers": ["to"], "share": ["information"], "information": ["over"], "long": ["distances."], "distances.": ["In"], "In": ["1989,"], "1989,": ["Tim"], "Tim": ["Berners-Lee"], "Berners-Lee": ["introduced"], "introduced": ["the", "in"], "World": ["Wide"], "Wide": ["Web,"], "Web,": ["which"], "revolutionized": ["communication"], "communication": ["and"], "made": ["the"], "accessible": ["to"], "public.": ["Today,"], "Today,": ["the"], "connects": ["billions"], "billions": ["of"], "devices,": ["serving"], "serving": ["as"], "vital": ["tool"], "tool": ["for"], "communication,": ["education,"], "education,": ["and"], "commerce.": ["Cryptocurrency"], "Cryptocurrency": ["is"], "digital": ["or"], "virtual": ["currency"], "currency": ["that"], "relies": ["on"], "cryptography": ["for"], "security.": ["Bitcoin,"], "Bitcoin,": ["introduced"], "2009,": ["was"], "was": ["the"], "first": ["decentralized"], "decentralized": ["cryptocurrency,", "and"], "cryptocurrency,": ["operating"], "operating": ["independently"], "independently": ["of"], "central": ["authority."], "authority.": ["Transactions"], "Transactions": ["are"], "recorded": ["on"], "blockchain,": ["a"], "distributed": ["ledger"], "ledger": ["system."], "While": ["cryptocurrencies"], "cryptocurrencies": ["have"], "potential": ["to"], "transform": ["traditional"], "traditional": ["financial"], "financial": ["systems,"], "raise": ["concerns"], "concerns": ["regarding"], "regarding": ["environmental"], "environmental": ["impact"], "need": ["for"], "regulatory": ["oversight."], "oversight.": ["Rainbows"], "Rainbows": ["are"], "optical": ["phenomena"], "phenomena": ["created"], "created": ["by"], "refraction,": ["dispersion,"], "dispersion,": ["and"], "reflection": ["of"], "within": ["water"], "droplets.": ["When"], "When": ["sunlight"], "enters": ["a"], "droplet,": ["it"], "bends": ["and"], "separates": ["into"], "component": ["colors,"], "colors,": ["reflects"], "reflects": ["off"], "off": ["the"], "droplet's": ["interior"], "interior": ["surface,"], "surface,": ["and"], "exits": ["to"], "visible": ["spectrum."], "spectrum.": ["This"], "This": ["natural"], "results": ["in"], "iconic": ["arc"], "arc": ["of"], "colors": ["that"], "appears": ["in"], "sky,": ["always"], "always": ["located"], "located": ["opposite"], "opposite": ["the"], "sun.": ["Sleep"]}